retwist/__init__.py
retwist/json_resource.py
retwist/param.py
retwist/param_resource.py
retwist/py.typed
retwist/route_site.py
retwist/util/__init__.py
retwist/util/limited_deferred_list.py
retwist/util/logs.py
retwist/util/sentry.py
retwist/util/static_file.py
retwist/util/wait_on_shutdown.py
retwist-0.4.1.dist-info/LICENSE
retwist-0.4.1.dist-info/METADATA
retwist-0.4.1.dist-info/WHEEL
retwist-0.4.1.dist-info/top_level.txt
retwist-0.4.1.dist-info/RECORD
