Metadata-Version: 2.1
Name: retwist
Version: 0.4.1
Summary: Write JSON REST APIs in the Twisted framework
Home-page: https://github.com/trustyou/retwist
Author: TrustYou
Author-email: development@trustyou.com
License: UNKNOWN
Download-URL: https://github.com/trustyou/retwist/archive/v0.4.1.tar.gz
Platform: UNKNOWN
Classifier: Development Status :: 5 - Production/Stable
Classifier: Intended Audience :: Developers
Classifier: License :: OSI Approved :: MIT License
Classifier: Natural Language :: English
Classifier: Programming Language :: Python :: 2.7
Classifier: Programming Language :: Python :: 3.6
Classifier: Programming Language :: Python :: 3.7
Classifier: Programming Language :: Python :: 3.8
Requires-Dist: twisted (>16.4)
Requires-Dist: typing ; python_version < "3.5"
Provides-Extra: jsonschema
Requires-Dist: jsonschema ; extra == 'jsonschema'
Requires-Dist: pyrsistent (<=0.16.1) ; (python_version < "3") and extra == 'jsonschema'
Provides-Extra: sentry
Requires-Dist: sentry-sdk ; extra == 'sentry'
